[
  {
    "full_name": "AkashSingh3031/The-Complete-FAANG-Preparation",
    "stargazers_count": 6571,
    "open_issues_count": 0,
    "forks_count": 1325
  },
  {
    "full_name": "vinitshahdeo/Hacktoberfest2021",
    "stargazers_count": 913,
    "open_issues_count": 84,
    "forks_count": 739
  },
  {
    "full_name": "vinitshahdeo/Hacktoberfest2021",
    "stargazers_count": 913,
    "open_issues_count": 84,
    "forks_count": 739
  },
  {
    "full_name": "iamjr15/open-sauced-goals",
    "stargazers_count": 0,
    "open_issues_count": 4,
    "forks_count": 0
  }
]